ualink_turbo64_v1_00_a/hdl/verilog/ualink_dpmem.v
/*******************************************************************************
 *
 *  Licence:
 *        This file is part of the NetFPGA 10G development base package.
 *
 *        This file is free code: you can redistribute it and/or modify it under
 *        the terms of the GNU Lesser General Public License version 2.1 as
 *        published by the Free Software Foundation.
 *
 *        This package is distributed in the hope that it will be useful, but
 *        WITHOUT ANY WARRANTY; without even the implied warranty of
 *        MERCHANTABILITY or FITNESS FOR A PARTICULAR PURPOSE.  See the GNU
 *        Lesser General Public License for more details.
 *
 *        You should have received a copy of the GNU Lesser General Public
 *        License along with the NetFPGA source package.  If not, see
 *        http://www.gnu.org/licenses/.
 *
 */

module dual_port_ram_8x64 
#(
        parameter DPADDR_WIDTH = 8,
    parameter DPDATA_WIDTH = 64,
    parameter DPDEPTH = (1 << DPADDR_WIDTH)
)
(
// Port A
input wire axi_aclk,  //common clock for port A and B
input  wire                     axi_resetn,      // enable for port A (active high)
input  wire                    we_a,      // write enable for port A (active high)
input  wire [DPADDR_WIDTH-1:0]    addr_a,
input  wire [DPDATA_WIDTH-1:0]    din_a,
output reg [DPDATA_WIDTH-1:0]    dout_a,

    // Port B

    input  wire                     we_b,      // write enable for port B (active high)
    input  wire [DPADDR_WIDTH-1:0]    addr_b,
    input  wire [DPDATA_WIDTH-1:0]    din_b,
    output reg  [DPDATA_WIDTH-1:0]    dout_b
);


// Memory declaration
reg [DPDATA_WIDTH-1:0] dpmem [0:DPDEPTH-1];
// Optional synthesis attribute for inferred block RAM (vendor-specific)
// (* ram_style = "block" *) reg [DATA_WIDTH-1:0] mem [0:DEPTH-1];
reg we_a_reg, we_b_reg;
reg [DPADDR_WIDTH-1:0] addr_a_reg, addr_b_reg;
reg [DPDATA_WIDTH-1:0] din_a_reg, din_b_reg;
reg [DPDATA_WIDTH-1:0] dout_a_reg;
reg [DPDATA_WIDTH-1:0] dout_b_reg;

always @(*) begin
        we_a_reg = we_a;
        we_b_reg = we_b;
        addr_a_reg = addr_a;
        addr_b_reg = addr_b;
        din_a_reg = din_a;
        din_b_reg = din_b;

end


// Port A logic (synchronous)
// Write-first behavior: when a write occurs on port A, dout_a returns the written data immediately.
  always @(posedge axi_aclk) begin
    if (!axi_resetn) begin  //initialize memory at reset
        dout_a <= "CAFEcafe";
        we_a_reg   <= 0;
        addr_a_reg <= 0;
        din_a_reg  <= 0;
        // dout_b <= 0;
        we_b_reg   <= 0;
        addr_b_reg <= 0;
        din_b_reg  <= 0;
        // for (i=0; i<DEPTH; i=i+1) begin
        //     mem[i] <= 0;
        // end
      end else begin
      if (we_a) begin
         dpmem[addr_a] <= din_a;
         dout_a <= "BEEFbeef"; //din_a;  // write-first: read returns new data
         end else begin
         dout_a <= dpmem[addr_a];    // synchronous read
         end
      end
    end
	 // Port B logic (synchronous)
  // Write-first behavior on port B as well.
/*  always @(posedge axi_aclk) begin
    if (axi_resetn) begin
      if (we_b) begin
        dpmem[addr_b] <= din_b;
        dout_b <= din_b;
      end else begin
        dout_b <= dpmem[addr_b];
        end
		end
  end*/
// Notes:
// - If both ports write the same address in the same cycle (in the same or different clocks), the final value is implementation-dependent / undefined.
// - To infer true dual-port block RAM on your FPGA, check vendor guidance (attributes or IP generator). The commented ram_style attribute is supported by some toolchains.
// - If you prefer read-first behavior, set dout <= mem[addr] before mem[addr] <= din (change assignment order in the write branch).
endmodule

ualink_turbo64_v1_00_a/hdl/verilog/ualink_dpmem_tb.v
`timescale 1ns / 1ps

module tb_dual_port_ram_8x64;

    // Parameters
    parameter DPADDR_WIDTH = 8;
    parameter DPDATA_WIDTH = 64;
    parameter DPDEPTH = (1 << DPADDR_WIDTH);
    parameter CLK_PERIOD = 10; // 10ns clock period (100MHz)

    // Testbench signals
    reg axi_aclk;
    reg axi_resetn;
    
    // Port A signals
    reg we_a;
    reg [DPADDR_WIDTH-1:0] addr_a;
    reg [DPDATA_WIDTH-1:0] din_a;
    wire [DPDATA_WIDTH-1:0] dout_a;
    
    // Port B signals
    reg we_b;
    reg [DPADDR_WIDTH-1:0] addr_b;
    reg [DPDATA_WIDTH-1:0] din_b;
    wire [DPDATA_WIDTH-1:0] dout_b;

    // Instantiate the DUT (Device Under Test)
    dual_port_ram_8x64 #(
        .DPADDR_WIDTH(DPADDR_WIDTH),
        .DPDATA_WIDTH(DPDATA_WIDTH),
        .DPDEPTH(DPDEPTH)
    ) dut (
        .axi_aclk(axi_aclk),
        .axi_resetn(axi_resetn),
        .we_a(we_a),
        .addr_a(addr_a),
        .din_a(din_a),
        .dout_a(dout_a),
        .we_b(we_b),
        .addr_b(addr_b),
        .din_b(din_b),
        .dout_b(dout_b)
    );

    // Clock generation
    initial begin
        axi_aclk = 0;
        forever #(CLK_PERIOD/2) axi_aclk = ~axi_aclk;
    end

    // Test stimulus
    initial begin
        // Initialize waveform dump
        $dumpfile("dual_port_ram.vcd");
        $dumpvars(0, tb_dual_port_ram_8x64);
        
        // Initialize signals
        axi_resetn = 0;
        we_a = 0;
        addr_a = 0;
        din_a = 0;
        we_b = 0;
        addr_b = 0;
        din_b = 0;
        
        $display("========================================");
        $display("Dual Port RAM Testbench Started");
        $display("========================================");
        
        // Apply reset
        #(CLK_PERIOD*2);
        axi_resetn = 1;
        #(CLK_PERIOD);
        
        // Test 1: Write to Port A, Read from Port A
        $display("\nTest 1: Port A Write and Read");
        write_port_a(8'h10, 64'hDEADBEEF_CAFEBABE);
        #(CLK_PERIOD);
        read_port_a(8'h10);
        #(CLK_PERIOD*2);
        
        // Test 2: Write to Port B, Read from Port B (if Port B write is implemented)
        $display("\nTest 2: Port B operations (Note: Port B write is commented out in module)");
        write_port_b(8'h20, 64'h12345678_9ABCDEF0);
        #(CLK_PERIOD);
        read_port_b(8'h20);
        #(CLK_PERIOD*2);
        
        // Test 3: Multiple writes to Port A
        $display("\nTest 3: Multiple writes to Port A");
        write_port_a(8'h00, 64'h0000000000000001);
        write_port_a(8'h01, 64'h0000000000000002);
        write_port_a(8'h02, 64'h0000000000000004);
        write_port_a(8'h03, 64'h0000000000000008);
        #(CLK_PERIOD);
        
        // Test 4: Sequential reads from Port A
        $display("\nTest 4: Sequential reads from Port A");
        read_port_a(8'h00);
        #(CLK_PERIOD);
        read_port_a(8'h01);
        #(CLK_PERIOD);
        read_port_a(8'h02);
        #(CLK_PERIOD);
        read_port_a(8'h03);
        #(CLK_PERIOD);
        
        // Test 5: Write-first behavior test
        $display("\nTest 5: Write-first behavior (should see BEEFbeef on write)");
        write_port_a(8'h50, 64'hAAAAAAAA_BBBBBBBB);
        #(CLK_PERIOD);
        $display("  dout_a after write = 0x%h (expected BEEFbeef)", dout_a);
        read_port_a(8'h50);
        #(CLK_PERIOD);
        $display("  dout_a after read = 0x%h (expected AAAAAAAA_BBBBBBBB)", dout_a);
        #(CLK_PERIOD);
        
        // Test 6: Simultaneous access to different addresses
        $display("\nTest 6: Simultaneous Port A and Port B access (different addresses)");
        fork
            write_port_a(8'hA0, 64'h1111111111111111);
            read_port_b(8'h10);
        join
        #(CLK_PERIOD*2);
        
        // Test 7: Same address access (potential conflict)
        $display("\nTest 7: Same address access from both ports");
        write_port_a(8'hFF, 64'hFFFFFFFFFFFFFFFF);
        #(CLK_PERIOD);
        fork
            read_port_a(8'hFF);
            read_port_b(8'hFF);
        join
        #(CLK_PERIOD*2);
        
/*
        
        // Test 9: Reset during operation
        $display("\nTest 9: Reset test");
        write_port_a(8'h55, 64'hBEFORE_RESET_DATA);
        #(CLK_PERIOD);
        axi_resetn = 0;
        #(CLK_PERIOD*2);
        $display("  dout_a during reset = 0x%h (expected CAFEcafe)", dout_a);
        axi_resetn = 1;
        #(CLK_PERIOD);
        read_port_a(8'h55);
        #(CLK_PERIOD*2);
   
        // Test 10: Burst write and read
        $display("\nTest 10: Burst write and read test");
        burst_write_port_a(8'h80, 16); // Write 16 locations starting at 0x80
        #(CLK_PERIOD);
        burst_read_port_a(8'h80, 16);  // Read back 16 locations
        #(CLK_PERIOD*2);
     */  
        // End simulation
        $display("\n========================================");
        $display("All tests completed!");
        $display("========================================");
        #(CLK_PERIOD*5);
        $finish;
    end

    // Task: Write to Port A
    task write_port_a;
        input [DPADDR_WIDTH-1:0] address;
        input [DPDATA_WIDTH-1:0] data;
        begin
            @(posedge axi_aclk);
            we_a = 1;
            addr_a = address;
            din_a = data;
            $display("  [Port A Write] Addr=0x%h, Data=0x%h", address, data);
            @(posedge axi_aclk);
            we_a = 0;
        end
    endtask

    // Task: Read from Port A
    task read_port_a;
        input [DPADDR_WIDTH-1:0] address;
        begin
            @(posedge axi_aclk);
            we_a = 0;
            addr_a = address;
            @(posedge axi_aclk);
            #1; // Small delay to allow output to settle
            $display("  [Port A Read]  Addr=0x%h, Data=0x%h", address, dout_a);
        end
    endtask

    // Task: Write to Port B
    task write_port_b;
        input [DPADDR_WIDTH-1:0] address;
        input [DPDATA_WIDTH-1:0] data;
        begin
            @(posedge axi_aclk);
            we_b = 1;
            addr_b = address;
            din_b = data;
            $display("  [Port B Write] Addr=0x%h, Data=0x%h", address, data);
            @(posedge axi_aclk);
            we_b = 0;
        end
    endtask

    // Task: Read from Port B
    task read_port_b;
        input [DPADDR_WIDTH-1:0] address;
        begin
            @(posedge axi_aclk);
            we_b = 0;
            addr_b = address;
            @(posedge axi_aclk);
            #1; // Small delay to allow output to settle
            $display("  [Port B Read]  Addr=0x%h, Data=0x%h", address, dout_b);
        end
    endtask

 /*   // Task: Burst write to Port A
    task burst_write_port_a;
        input [DPADDR_WIDTH-1:0] start_addr;
        input integer count;
        integer i;
        begin
            for (i = 0; i < count; i = i + 1) begin
                write_port_a(start_addr + i, {32'h0000, 32'(start_addr + i)});
            end
        end
    endtask

    // Task: Burst read from Port A
    task burst_read_port_a;
        input [DPADDR_WIDTH-1:0] start_addr;
        input integer count;
        integer i;
        begin
            for (i = 0; i < count; i = i + 1) begin
                read_port_a(start_addr + i);
            end
        end
    endtask
*/
    // Monitor for detecting unexpected changes
    always @(posedge axi_aclk) begin
        if (axi_resetn && we_a) begin
            #1;
            if (dout_a !== 64'hBEEFbeef) begin
                $display("  WARNING: Write-first behavior violation at time %t", $time);
            end
        end
    end

endmodule

ualink_turbo64_v1_00_a/hdl/verilog/dual_port_ram.vcd
$date
	Wed Nov 19 12:23:34 2025
$end
$version
	Icarus Verilog
$end
$timescale
	1ps
$end
$scope module tb_dual_port_ram_8x64 $end
$var wire 64 ! dout_b [63:0] $end
$var wire 64 " dout_a [63:0] $end
$var parameter 32 # CLK_PERIOD $end
$var parameter 32 $ DPADDR_WIDTH $end
$var parameter 32 % DPDATA_WIDTH $end
$var parameter 40 & DPDEPTH $end
$var reg 8 ' addr_a [7:0] $end
$var reg 8 ( addr_b [7:0] $end
$var reg 1 ) axi_aclk $end
$var reg 1 * axi_resetn $end
$var reg 64 + din_a [63:0] $end
$var reg 64 , din_b [63:0] $end
$var reg 1 - we_a $end
$var reg 1 . we_b $end
$scope module dut $end
$var wire 8 / addr_a [7:0] $end
$var wire 8 0 addr_b [7:0] $end
$var wire 1 ) axi_aclk $end
$var wire 1 * axi_resetn $end
$var wire 64 1 din_a [63:0] $end
$var wire 64 2 din_b [63:0] $end
$var wire 1 - we_a $end
$var wire 1 . we_b $end
$var parameter 32 3 DPADDR_WIDTH $end
$var parameter 32 4 DPDATA_WIDTH $end
$var parameter 40 5 DPDEPTH $end
$var reg 8 6 addr_a_reg [7:0] $end
$var reg 8 7 addr_b_reg [7:0] $end
$var reg 64 8 din_a_reg [63:0] $end
$var reg 64 9 din_b_reg [63:0] $end
$var reg 64 : dout_a [63:0] $end
$var reg 64 ; dout_b [63:0] $end
$var reg 1 < we_a_reg $end
$var reg 1 = we_b_reg $end
$upscope $end
$scope task read_port_a $end
$var reg 8 > address [7:0] $end
$upscope $end
$scope task read_port_b $end
$var reg 8 ? address [7:0] $end
$upscope $end
$scope task write_port_a $end
$var reg 8 @ address [7:0] $end
$var reg 64 A data [63:0] $end
$upscope $end
$scope task write_port_b $end
$var reg 8 B address [7:0] $end
$var reg 64 C data [63:0] $end
$upscope $end
$upscope $end
$enddefinitions $end
$comment Show the parameter values. $end
$dumpall
b100000000 5
b1000000 4
b1000 3
b100000000 &
b1000000 %
b1000 $
b1010 #
$end
#0
$dumpvars
bx C
bx B
bx A
bx @
bx ?
bx >
0=
0<
bx ;
bx :
b0 9
b0 8
b0 7
b0 6
b0 2
b0 1
b0 0
b0 /
0.
0-
b0 ,
b0 +
0*
0)
b0 (
b0 '
bx "
bx !
$end
#5000
b100001101000001010001100100010101100011011000010110011001100101 "
b100001101000001010001100100010101100011011000010110011001100101 :
1)
#10000
0)
#15000
1)
#20000
0)
1*
#25000
bx "
bx :
1)
#30000
0)
b1101111010101101101111101110111111001010111111101011101010111110 A
b10000 @
#35000
b1101111010101101101111101110111111001010111111101011101010111110 "
b1101111010101101101111101110111111001010111111101011101010111110 :
b1101111010101101101111101110111111001010111111101011101010111110 8
b10000 6
1<
b1101111010101101101111101110111111001010111111101011101010111110 +
b1101111010101101101111101110111111001010111111101011101010111110 1
b10000 '
b10000 /
1-
1)
#40000
0)
#45000
0<
0-
1)
#50000
0)
#55000
1)
b10000 >
#60000
0)
#65000
1)
#70000
0)
#75000
1)
#80000
0)
#85000
1)
#86000
b1001000110100010101100111100010011010101111001101111011110000 C
b100000 B
#90000
0)
#95000
b1001000110100010101100111100010011010101111001101111011110000 !
b1001000110100010101100111100010011010101111001101111011110000 ;
b1001000110100010101100111100010011010101111001101111011110000 9
b100000 7
1=
b1001000110100010101100111100010011010101111001101111011110000 ,
b1001000110100010101100111100010011010101111001101111011110000 2
b100000 (
b100000 0
1.
1)
#100000
0)
#105000
0=
0.
1)
#110000
0)
#115000
1)
b100000 ?
#120000
0)
#125000
1)
#130000
0)
#135000
1)
#140000
0)
#145000
1)
#146000
b1 A
b0 @
#150000
0)
#155000
b1 "
b1 :
b1 8
b0 6
1<
b1 +
b1 1
b0 '
b0 /
1-
1)
#160000
0)
#165000
0<
b10 A
b1 @
0-
1)
#170000
0)
#175000
b10 "
b10 :
b10 8
b1 6
1<
b10 +
b10 1
b1 '
b1 /
1-
1)
#180000
0)
#185000
0<
b100 A
b10 @
0-
1)
#190000
0)
#195000
b100 "
b100 :
b100 8
b10 6
1<
b100 +
b100 1
b10 '
b10 /
1-
1)
#200000
0)
#205000
0<
b1000 A
b11 @
0-
1)
#210000
0)
#215000
b1000 "
b1000 :
b1000 8
b11 6
1<
b1000 +
b1000 1
b11 '
b11 /
1-
1)
#220000
0)
#225000
0<
0-
1)
#230000
0)
#235000
b1 "
b1 :
b0 6
b0 '
b0 /
1)
b0 >
#240000
0)
#245000
1)
#250000
0)
#255000
1)
#256000
b1 >
#260000
0)
#265000
b10 "
b10 :
b1 6
b1 '
b1 /
1)
#270000
0)
#275000
1)
#280000
0)
#285000
1)
#286000
b10 >
#290000
0)
#295000
b100 "
b100 :
b10 6
b10 '
b10 /
1)
#300000
0)
#305000
1)
#310000
0)
#315000
1)
#316000
b11 >
#320000
0)
#325000
b1000 "
b1000 :
b11 6
b11 '
b11 /
1)
#330000
0)
#335000
1)
#340000
0)
#345000
1)
#346000
b1010101010101010101010101010101010111011101110111011101110111011 A
b1010000 @
#350000
0)
#355000
b1010101010101010101010101010101010111011101110111011101110111011 "
b1010101010101010101010101010101010111011101110111011101110111011 :
b1010101010101010101010101010101010111011101110111011101110111011 8
b1010000 6
1<
b1010101010101010101010101010101010111011101110111011101110111011 +
b1010101010101010101010101010101010111011101110111011101110111011 1
b1010000 '
b1010000 /
1-
1)
#360000
0)
#365000
0<
0-
1)
#370000
0)
#375000
1)
b1010000 >
#380000
0)
#385000
1)
#390000
0)
#395000
1)
#400000
0)
#405000
1)
#406000
b1000100010001000100010001000100010001000100010001000100010001 A
b10100000 @
b10000 ?
#410000
0)
#415000
b1101111010101101101111101110111111001010111111101011101010111110 !
b1101111010101101101111101110111111001010111111101011101010111110 ;
b1000100010001000100010001000100010001000100010001000100010001 "
b1000100010001000100010001000100010001000100010001000100010001 :
b1000100010001000100010001000100010001000100010001000100010001 8
b10000 7
b10100000 6
1<
b10000 (
b10000 0
b1000100010001000100010001000100010001000100010001000100010001 +
b1000100010001000100010001000100010001000100010001000100010001 1
b10100000 '
b10100000 /
1-
1)
#420000
0)
#425000
0<
0-
1)
#430000
0)
#435000
1)
#440000
0)
#445000
1)
#446000
b1111111111111111111111111111111111111111111111111111111111111111 A
b11111111 @
#450000
0)
#455000
b1111111111111111111111111111111111111111111111111111111111111111 "
b1111111111111111111111111111111111111111111111111111111111111111 :
b1111111111111111111111111111111111111111111111111111111111111111 8
b11111111 6
1<
b1111111111111111111111111111111111111111111111111111111111111111 +
b1111111111111111111111111111111111111111111111111111111111111111 1
b11111111 '
b11111111 /
1-
1)
#460000
0)
#465000
0<
0-
1)
#470000
0)
#475000
b1111111111111111111111111111111111111111111111111111111111111111 !
b1111111111111111111111111111111111111111111111111111111111111111 ;
b11111111 7
b11111111 (
b11111111 0
1)
b11111111 >
b11111111 ?
